{
  "strings": [
    {
      "label": "ChromeMinimize",
      "string": ""
    },
    {
      "label": "ChromeMaximize",
      "string": ""
    },
    {
      "label": "ChromeClose",
      "string": ""
    },
    {
      "label": "Search Text",
      "string": "Search"
    },
    {
      "label": "Search",
      "string": ""
    },
    {
      "label": "Icon",
      "string": ""
    },
    {
      "label": "Icon",
      "string": ""
    },
    {
      "label": "Text",
      "string": "Axis camera station client"
    },
    {
      "label": "Text",
      "string": "Preview"
    },
    {
      "label": "Search",
      "string": ""
    },
    {
      "label": "Text",
      "string": "Configuration"
    },
    {
      "label": "Text",
      "string": "Text"
    },
    {
      "label": "Text",
      "string": "Text"
    },
    {
      "label": "Text",
      "string": "Text"
    },
    {
      "label": "Text",
      "string": "Text"
    },
    {
      "label": "Text",
      "string": "Devices"
    },
    {
      "label": "Text",
      "string": "Storage"
    },
    {
      "label": "Text",
      "string": "Recordings and events"
    },
    {
      "label": "Text",
      "string": "Server"
    },
    {
      "label": "Text",
      "string": "Licenses"
    },
    {
      "label": "Text",
      "string": "Security"
    },
    {
      "label": "Text",
      "string": "Doors and Zones"
    },
    {
      "label": "Text",
      "string": "Identification profile"
    },
    {
      "label": "Text",
      "string": "Encrypted communication"
    },
    {
      "label": "Required asterisk",
      "string": "*"
    },
    {
      "label": "Text",
      "string": "Access control"
    },
    {
      "label": "Text",
      "string": "Smart search"
    },
    {
      "label": "Text",
      "string": "System health monitoring"
    },
    {
      "label": "Doors & Zones.",
      "string": "Doors & Zones."
    },
    {
      "label": "Text",
      "string": "Doors"
    },
    {
      "label": "Text",
      "string": "Zones"
    },
    {
      "label": "Text",
      "string": "Third tab"
    },
    {
      "label": "Text",
      "string": "Fourth tab"
    },
    {
      "label": "Text",
      "string": "Fifth tab"
    },
    {
      "label": "Text",
      "string": "Text"
    },
    {
      "label": "add",
      "string": "Add"
    },
    {
      "label": "Placeholder text",
      "string": "Placeholder text"
    },
    {
      "label": "Entered text",
      "string": "Entered text"
    },
    {
      "label": "Placeholder text",
      "string": "Placeholder text"
    },
    {
      "label": "Entered text",
      "string": "Entered text"
    },
    {
      "label": "Text",
      "string": "Delete"
    },
    {
      "label": "Text",
      "string": "Edit"
    },
    {
      "label": "Text",
      "string": "Pin chart"
    },
    {
      "label": "Text",
      "string": "Identification profile"
    },
    {
      "label": "Text",
      "string": "Reader connection"
    },
    {
      "label": "Text",
      "string": "Text"
    },
    {
      "label": "Text",
      "string": "Syncronize"
    },
    {
      "label": "Text",
      "string": "Advanced"
    },
    {
      "label": "Placeholder text",
      "string": "Placeholder text"
    },
    {
      "label": "Entered text",
      "string": "Entered text"
    },
    {
      "label": "Text",
      "string": "Label"
    },
    {
      "label": "Required asterisk",
      "string": "*"
    },
    {
      "label": "Header",
      "string": "Name"
    },
    {
      "label": "Header",
      "string": "Type"
    },
    {
      "label": "Header",
      "string": "Door controller"
    },
    {
      "label": "Header",
      "string": "Adress"
    },
    {
      "label": "Header",
      "string": "Side A"
    },
    {
      "label": "Header",
      "string": "Side  B"
    },
    {
      "label": "Header",
      "string": "Identification profile"
    },
    {
      "label": "Header",
      "string": "Card formats & PIN"
    },
    {
      "label": "Header",
      "string": "Status"
    },
    {
      "label": "Text",
      "string": "Label"
    },
    {
      "label": "Required asterisk",
      "string": "*"
    },
    {
      "label": "Content",
      "string": "Front door"
    },
    {
      "label": "Text",
      "string": "Door"
    },
    {
      "label": "Content",
      "string": "AXIS A1601 (1)"
    },
    {
      "label": "Description",
      "string": "196.255.64.64"
    },
    {
      "label": "Content",
      "string": "Zone 1"
    },
    {
      "label": "Content",
      "string": "Zone 2"
    },
    {
      "label": "Text",
      "string": "PIN code"
    },
    {
      "label": "Text",
      "string": "System"
    },
    {
      "label": "Text",
      "string": "Syncronizing 24%..."
    },
    {
      "label": "Text",
      "string": "Label"
    },
    {
      "label": "Required asterisk",
      "string": "*"
    },
    {
      "label": "Content",
      "string": "Back door"
    },
    {
      "label": "Text",
      "string": "Gate"
    },
    {
      "label": "Content",
      "string": "AXIS A1601 (1)"
    },
    {
      "label": "Description",
      "string": "196.255.64.64"
    },
    {
      "label": "Content",
      "string": "Zone 1"
    },
    {
      "label": "Content",
      "string": "Zone 2"
    },
    {
      "label": "Text",
      "string": "PIN code"
    },
    {
      "label": "Text",
      "string": "PIN & Code"
    },
    {
      "label": "Text",
      "string": "Online"
    },
    {
      "label": "Text",
      "string": "Label"
    },
    {
      "label": "Required asterisk",
      "string": "*"
    },
    {
      "label": "Content",
      "string": "Service door"
    },
    {
      "label": "Text",
      "string": "Wireless door"
    },
    {
      "label": "Content",
      "string": "AXIS A1601 (1)"
    },
    {
      "label": "Description",
      "string": "196.255.64.64"
    },
    {
      "label": "Content",
      "string": "Zone 1"
    },
    {
      "label": "Content",
      "string": "Zone 2"
    },
    {
      "label": "Text",
      "string": "PIN code"
    },
    {
      "label": "Text",
      "string": "AVLP & Card"
    },
    {
      "label": "Text",
      "string": "Offline"
    },
    {
      "label": "Text",
      "string": "Label"
    },
    {
      "label": "Required asterisk",
      "string": "*"
    },
    {
      "label": "Content",
      "string": "Basement"
    },
    {
      "label": "Text",
      "string": "Floor"
    },
    {
      "label": "Content",
      "string": "AXIS A1601 (1)"
    },
    {
      "label": "Description",
      "string": "196.255.64.64"
    },
    {
      "label": "Content",
      "string": "Zone 1"
    },
    {
      "label": "Content",
      "string": "Zone 2"
    },
    {
      "label": "Text",
      "string": "PIN code"
    },
    {
      "label": "Text",
      "string": "QR"
    },
    {
      "label": "Text",
      "string": "Offline"
    }
  ],
  "ChromeMinimize": "",
  "ChromeMaximize": "",
  "ChromeClose": "",
  "Search Text": "Search",
  "Search": "",
  "Icon": "",
  "Text": "Offline",
  "Required asterisk": "*",
  "Doors & Zones.": "Doors & Zones.",
  "add": "Add",
  "Placeholder text": "Placeholder text",
  "Entered text": "Entered text",
  "placeholderText": "Placeholder text",
  "Header": "Status",
  "Content": "Zone 2",
  "Description": "196.255.64.64"
}