{
  "ChromeMinimize": "",
  "ChromeMaximize": "",
  "ChromeClose": "",
  "Text": "Text",
  "Icon": "",
  "ChevronUpMed": "",
  "Clear12": "",
  "Add": "",
  "String-button": "Cancel",
  "String-chevronRight": "",
  "Search": "Search",
  "Card title": "Sensors",
  "Side B": "Side B",
  "String-cell-primary": "Door monitor",
  "String-cell-secondary": "Tim Deboar",
  "Side A": "Side A",
  "Placeholder text": "Placeholder text",
  "Entered text": "Entered text",
  "Required asterisk": "*",
  "String-label": "Reader adress",
  "String-title": "OSDP, RS485 half duplex",
  "Value": "4",
  "String-subtext": "Do you want to send this message without a subject?",
  "String-swap-placeholder": "SWAP WITH CONTENT COMPONENT",
  "String": "1",
  "String-icon-ChevronDown": ""
}